Solos/__init__.py
Solos/_version.py
Solos/skeleton.py
Solos/urmp.py
Solos/utils.py
Solos/SoP/__init__.py
Solos/SoP/config/__init__.py
Solos/SoP/config/deep_config.py
Solos/SoP/config/transforms.py
Solos/SoP/models/__init__.py
Solos/SoP/models/audio_net.py
Solos/SoP/models/criterion.py
Solos/SoP/models/synthesizer_net.py
Solos/SoP/models/vision_net.py
Solos/SoP/utils/__init__.py
Solos/SoP/utils/base_dataset.py
Solos/SoP/utils/dataset.py
Solos/SoP/utils/loss.py
Solos/SoP/utils/readers.py
Solos/json_files/__init__.py
Solos/json_files/solos_ids.json
Solos/json_files/solos_timestamps.json
Solos/skeleton_files/__init__.py
Solos/skeleton_files/skeleton_dict.json
dev/3_rencode25_dataset.py
dev/5_skeleton2binary.py
dev/6_rectify_skeleton.py
dev/__init__.py
dev/crop_upperbody_yuv420.py
dev/extract_audio.py
dev/ffprobe_test.py
dev/full_check.py
dev/get_csv.py
test/__init__.py
test/test_SoP.py
test/test_library.py
solos-0.4.1.dist-info/METADATA
solos-0.4.1.dist-info/WHEEL
solos-0.4.1.dist-info/top_level.txt
solos-0.4.1.dist-info/RECORD
